httpfs/__init__.py
httpfs/_version.py
httpfs/fs.py
httpfs/opener.py
httpfs-0.0.1.dist-info/LICENSE
httpfs-0.0.1.dist-info/METADATA
httpfs-0.0.1.dist-info/WHEEL
httpfs-0.0.1.dist-info/entry_points.txt
httpfs-0.0.1.dist-info/top_level.txt
httpfs-0.0.1.dist-info/RECORD
