Metadata-Version: 2.1
Name: httpfs
Version: 0.0.1
Summary: Read file over HTTP protocol via python file system 2 interface
Home-page: https://github.com/moremoban/httpfs
Author: C.W.
Author-email: wangc_2011@hotmail.com
License: mit
Download-URL: https://github.com/moremoban/httpfs/archive/0.0.1.tar.gz
Keywords: python
Platform: UNKNOWN
Classifier: Topic :: Software Development :: Libraries
Classifier: Programming Language :: Python
Classifier: Intended Audience :: Developers
Classifier: Programming Language :: Python :: 2.6
Classifier: Programming Language :: Python :: 2.7
Classifier: Programming Language :: Python :: 3.3
Classifier: Programming Language :: Python :: 3.4
Classifier: Programming Language :: Python :: 3.5
Classifier: Programming Language :: Python :: 3.6
Classifier: Programming Language :: Python :: 3.7
Classifier: Programming Language :: Python :: 3.8
Requires-Dist: fs
Requires-Dist: httpx
